DataConversion.py
__init__.py
accessi.py
accessi-0.0.8.dist-info/LICENSE
accessi-0.0.8.dist-info/METADATA
accessi-0.0.8.dist-info/WHEEL
accessi-0.0.8.dist-info/top_level.txt
accessi-0.0.8.dist-info/RECORD
