Metadata-Version: 2.1
Name: accessi
Version: 0.0.8
Summary: Library for Siemens Access-i MR Scanner Interface to integrate and control the MR Scanner.
Author-email: Martin Reinok <m.reinok@student.utwente.nl>
Project-URL: Homepage, https://gitlab.utwente.nl/s2981416/accessi-library
Project-URL: Issues, https://gitlab.utwente.nl/s2981416/accessi-library/-/issues
Classifier: Programming Language :: Python :: 3
Classifier: License :: OSI Approved :: MIT License
Classifier: Operating System :: OS Independent
Requires-Python: >=3.8
License-File: LICENSE
Requires-Dist: numpy
Requires-Dist: websockets
Requires-Dist: urllib3
Requires-Dist: requests
